igruha/__init__.py
igruha-3.1.dist-info/METADATA
igruha-3.1.dist-info/WHEEL
igruha-3.1.dist-info/top_level.txt
igruha-3.1.dist-info/RECORD
