Metadata-Version: 2.1
Name: igruha
Version: 3.1
Summary: Torrent-Igruha SDK Python
Home-page: UNKNOWN
Author: lordcodes
Author-email: lordgrief176@gmail.com
License: UNKNOWN
Platform: UNKNOWN
Requires-Dist: requests
Requires-Dist: lxml
Requires-Dist: beautifulsoup4
Requires-Dist: cfscrape
